{"ns:m.02rqcwj":{"ns:common.topic.description":["LSE is a programming language developed at Supélec in the late 1970s/early 1980s. It is similar to the BASIC, except with French-language instead of English-language keywords. It was derived from an earlier language called LSD, also developed at Supélec. It is most commonly said to be an acronym for Langage Symbolique d'Enseignement, but other expansions are also known\\nIt originally flourished due to support from the French National Ministry of Education, but declined as the Ministry lost interest. It went through a number of revisions; earlier versions of LSE lacked full support for structured programming, which later version added, along with exception handling."],"rdfs:label":["LSE"],"ns:common.topic.article":[{"ns:common.document.text":["LSE (Langage symbolique d'enseignement) is a programming language developed at Supélec in the late 1970s/early 1980s. It is similar to the BASIC, except with French-language instead of English-language keywords. It was derived from an earlier language called LSD, also developed at Supélec. It is most commonly said to be an acronym for Langage Symbolique d'Enseignement (Symbolic Teaching Language), but other expansions are also known (e.g. Langage de Sup-Élec, or the more cynical Langage Sans Espoir (hopeless language))\\nIt originally flourished due to support from the French National Ministry of Education, but declined as the Ministry lost interest. It went through a number of revisions; earlier versions of LSE lacked full support for structured programming, which later version added, along with exception-handling."],"ns:common.document.source_uri":["<http://wp/en/11730351>"],"rdf:type":["ns:common.document"]}],"ns:type.object.name":["LSE"],"rdf:type":["ns:computer.programming_language"],"ns:kg.object_profile.prominent_type":["ns:computer.programming_language"],"ns:common.topic.notable_for":["ns:g.1255_4zc5"],"ns:common.topic.notable_types":["ns:m.01xrl_t"]}}